missingValues/__init__.py
missingValues/missingValuesArsh.py
missingValuesArshdeepsk-0.0.1.dist-info/LICENSE
missingValuesArshdeepsk-0.0.1.dist-info/METADATA
missingValuesArshdeepsk-0.0.1.dist-info/WHEEL
missingValuesArshdeepsk-0.0.1.dist-info/entry_points.txt
missingValuesArshdeepsk-0.0.1.dist-info/top_level.txt
missingValuesArshdeepsk-0.0.1.dist-info/RECORD
