Metadata-Version: 2.1
Name: missingValuesArshdeepsk
Version: 0.0.1
Summary: Use this package to replace missing values in your data by mean of columns
Home-page: https://github.com/arshdeepsk/missingValuesArsh
Author: Arshdeep Singh
Author-email: akawatra_be17@thapar.edu
License: UNKNOWN
Platform: UNKNOWN
Classifier: Programming Language :: Python :: 3
Classifier: License :: OSI Approved :: MIT License
Classifier: Operating System :: OS Independent
